wafer_map/__init__.py
wafer_map/__main__.py
wafer_map/example.py
wafer_map/gen_fake_data.py
wafer_map/wm_app.py
wafer_map/wm_constants.py
wafer_map/wm_core.py
wafer_map/wm_frame.py
wafer_map/wm_info.py
wafer_map/wm_legend.py
wafer_map/wm_utils.py
wafer_map-1.2.0.dist-info/LICENSE
wafer_map-1.2.0.dist-info/METADATA
wafer_map-1.2.0.dist-info/WHEEL
wafer_map-1.2.0.dist-info/top_level.txt
wafer_map-1.2.0.dist-info/RECORD
