Metadata-Version: 2.1
Name: wafer-map
Version: 1.2.0
Summary: Semiconductor Wafer Mapping
Author: Douglas Thor
Author-email: Douglas Thor <doug.thor@gmail.com>
License: GNU GENERAL PUBLIC LICENSE
Project-URL: Source Code, https://github.com/dougthor42/wafer_map
Project-URL: Changelog, https://github.com/dougthor42/wafer_map/blob/master/CHANGELOG.md
Project-URL: Bug Tracker, https://github.com/dougthor42/wafer_map/issues
Classifier: Development Status :: 5 - Production/Stable
Classifier: Intended Audience :: Manufacturing
Classifier: Intended Audience :: Science/Research
Classifier: License :: OSI Approved :: GNU General Public License v3 or later (GPLv3+)
Classifier: Operating System :: OS Independent
Classifier: Programming Language :: Python :: 3
Classifier: Topic :: Scientific/Engineering
Classifier: Topic :: Scientific/Engineering :: Information Analysis
Classifier: Topic :: Scientific/Engineering :: Visualization
Requires-Python: >=3.8
License-File: LICENSE
Requires-Dist: wxPython <4.3,>=4.0.0
Requires-Dist: numpy <2.0,>=1.12.1
Requires-Dist: colour <0.2,>=0.1.4
Provides-Extra: all
Requires-Dist: wafer-map[build,dev,docs] ; extra == 'all'
Provides-Extra: build
Requires-Dist: build ==1.0.3 ; extra == 'build'
Requires-Dist: setuptools ==68.2.2 ; extra == 'build'
Requires-Dist: wheel ==0.41.3 ; extra == 'build'
Provides-Extra: dev
Requires-Dist: coverage[toml] ==7.3.2 ; extra == 'dev'
Requires-Dist: pre-commit ==3.5.0 ; extra == 'dev'
Requires-Dist: pytest-cov ==4.1.0 ; extra == 'dev'
Requires-Dist: pytest ==7.4.3 ; extra == 'dev'
Provides-Extra: docs
Requires-Dist: sphinx ==7.1.2 ; extra == 'docs'
Requires-Dist: sphinx-rtd-theme ==1.3.0 ; extra == 'docs'
